README.md
pyproject.toml
setup.cfg
setup.py
rtu_mirea_vuc_schedule_client/__init__.py
rtu_mirea_vuc_schedule_client/api_client.py
rtu_mirea_vuc_schedule_client/api_response.py
rtu_mirea_vuc_schedule_client/configuration.py
rtu_mirea_vuc_schedule_client/exceptions.py
rtu_mirea_vuc_schedule_client/py.typed
rtu_mirea_vuc_schedule_client/rest.py
rtu_mirea_vuc_schedule_client.egg-info/PKG-INFO
rtu_mirea_vuc_schedule_client.egg-info/SOURCES.txt
rtu_mirea_vuc_schedule_client.egg-info/dependency_links.txt
rtu_mirea_vuc_schedule_client.egg-info/requires.txt
rtu_mirea_vuc_schedule_client.egg-info/top_level.txt
rtu_mirea_vuc_schedule_client/api/__init__.py
rtu_mirea_vuc_schedule_client/api/schedule_api.py
rtu_mirea_vuc_schedule_client/api/workbook_api.py
rtu_mirea_vuc_schedule_client/models/__init__.py
rtu_mirea_vuc_schedule_client/models/course_dir.py
rtu_mirea_vuc_schedule_client/models/day.py
rtu_mirea_vuc_schedule_client/models/day_result.py
rtu_mirea_vuc_schedule_client/models/http_validation_error.py
rtu_mirea_vuc_schedule_client/models/lesson.py
rtu_mirea_vuc_schedule_client/models/platoon.py
rtu_mirea_vuc_schedule_client/models/schedule_result.py
rtu_mirea_vuc_schedule_client/models/shape.py
rtu_mirea_vuc_schedule_client/models/subject.py
rtu_mirea_vuc_schedule_client/models/validation_error.py
rtu_mirea_vuc_schedule_client/models/validation_error_loc_inner.py
rtu_mirea_vuc_schedule_client/models/week_schedule.py
rtu_mirea_vuc_schedule_client/models/week_schedule_result.py
rtu_mirea_vuc_schedule_client/models/workbook_file.py
rtu_mirea_vuc_schedule_client/models/workbook_settings.py
test/test_course_dir.py
test/test_day.py
test/test_day_result.py
test/test_http_validation_error.py
test/test_lesson.py
test/test_platoon.py
test/test_schedule_api.py
test/test_schedule_result.py
test/test_shape.py
test/test_subject.py
test/test_validation_error.py
test/test_validation_error_loc_inner.py
test/test_week_schedule.py
test/test_week_schedule_result.py
test/test_workbook_api.py
test/test_workbook_file.py
test/test_workbook_settings.py