Metadata-Version: 2.1
Name: rtu-mirea-vuc-schedule-client
Version: 1.0.8
Summary: rtu mirea vuc schedule
Home-page: 
Author: OpenAPI Generator community
Author-email: team@openapitools.org
Keywords: OpenAPI,OpenAPI-Generator,rtu mirea vuc schedule
